setup.py
parseable/__init__.py
parseable.egg-info/PKG-INFO
parseable.egg-info/SOURCES.txt
parseable.egg-info/dependency_links.txt
parseable.egg-info/requires.txt
parseable.egg-info/top_level.txt