Metadata-Version: 1.1
Name: parseable
Version: 1.0b3
Summary: map datastructures to objects with data validation
Home-page: https://github.com/nlm/parseable
Author: Nicolas Limage
Author-email: github@xephon.org
License: MIT
Keywords: datastructure parsing validation
Platform: UNKNOWN
Classifier: Development Status :: 4 - Beta
Classifier: Intended Audience :: Developers
Classifier: License :: OSI Approved :: MIT License
Classifier: Operating System :: OS Independent
Classifier: Programming Language :: Python
